{
  "persons": [
    {
      "name": "ada lovelace",
      "number": "81273981273921",
      "id": 2
    },
    {
      "name": "Dan Abramov",
      "number": "12-43-234345",
      "id": 3
    },
    {
      "name": "benjamin",
      "number": "98688332",
      "id": 5
    },
    {
      "name": "raya",
      "number": "81273917293",
      "id": 6
    },
    {
      "name": "renault ",
      "number": "912321",
      "id": 7
    },
    {
      "name": "benji",
      "number": "921830921",
      "id": 8
    },
    {
      "name": "dan",
      "number": "98790",
      "id": 9
    }
  ]
}